{
  "kind": "collectionType",
  "collectionName": "stays",
  "info": {
    "name": "stay"
  },
  "options": {
    "increments": true,
    "timestamps": true
  },
  "attributes": {
    "name": {
      "type": "string",
      "required": true
    },
    "email": {
      "type": "email"
    },
    "location": {
      "type": "string"
    },
    "website": {
      "type": "string"
    },
    "phone": {
      "type": "biginteger"
    },
    "text": {
      "type": "biginteger"
    },
    "description": {
      "type": "text"
    },
    "image": {
      "model": "file",
      "via": "related",
      "allowedTypes": [
        "images"
      ],
      "plugin": "upload",
      "required": false
    },
    "audioUrl": {
      "type": "string"
    },
    "social": {
      "type": "component",
      "repeatable": true,
      "component": "social.social-links"
    }
  }
}
